dosts/AtmosphericDensity.py
dosts/CoordinateTransformations.py
dosts/CrudeInitialConditions.py
dosts/ExtendedKalmanFilters.py
dosts/ModelDynamics.py
dosts/NumericalIntegrator.py
dosts/PredictorIntegrator.py
dosts/RadarModule.py
dosts/Visualiser.py
dosts/WriteToFiles.py
dosts/__init__.py
dosts/__main__.py
dosts-1.0.0.dist-info/licenses/LICENSE
dosts-1.0.0.dist-info/METADATA
dosts-1.0.0.dist-info/WHEEL
dosts-1.0.0.dist-info/entry_points.txt
dosts-1.0.0.dist-info/top_level.txt
dosts-1.0.0.dist-info/RECORD
