Metadata-Version: 2.4
Name: dosts
Version: 1.0.0
Summary: A Python-based De-Orbiting Satellite Tracking System (D-OSTS)
Author: Jai Bharaj, Tom Miller, David Dukov, Linan Yang, Kunlin Cai
License: MIT
Classifier: Programming Language :: Python :: 3
Classifier: License :: OSI Approved :: MIT License
Classifier: Operating System :: OS Independent
Classifier: Intended Audience :: Science/Research
Classifier: Topic :: Scientific/Engineering :: Physics
Requires-Python: >=3.8
License-File: LICENSE
Requires-Dist: numpy
Requires-Dist: matplotlib
Requires-Dist: scipy
Requires-Dist: ussa1976
Dynamic: license-file
